rabbitmqadmin/__init__.py
rabbitmqadmin/upstream/rabbitmqadmin.py
rabbitmqadmin/upstream/rabbitmqadmin_original.py
rabbitmqadmin_client-0.0.2.dist-info/LICENSE
rabbitmqadmin_client-0.0.2.dist-info/METADATA
rabbitmqadmin_client-0.0.2.dist-info/WHEEL
rabbitmqadmin_client-0.0.2.dist-info/entry_points.txt
rabbitmqadmin_client-0.0.2.dist-info/top_level.txt
rabbitmqadmin_client-0.0.2.dist-info/RECORD
